peristyle/__init__.py
peristyle/__main__.py
tests/__init__.py
peristyle-0.0.1.dist-info/LICENSE
peristyle-0.0.1.dist-info/METADATA
peristyle-0.0.1.dist-info/WHEEL
peristyle-0.0.1.dist-info/entry_points.txt
peristyle-0.0.1.dist-info/top_level.txt
peristyle-0.0.1.dist-info/RECORD
